qinspect/__init__.py
qinspect/middleware.py
django_queryinspect-1.1.0.dist-info/METADATA
django_queryinspect-1.1.0.dist-info/WHEEL
django_queryinspect-1.1.0.dist-info/top_level.txt
django_queryinspect-1.1.0.dist-info/RECORD
