Metadata-Version: 2.1
Name: django-queryinspect
Version: 1.1.0
Summary: Django Query Inspector
Home-page: https://github.com/dobarkod/django-queryinspect
Author: Senko Rasic
Author-email: senko.rasic@goodcode.io
License: MIT
Platform: UNKNOWN
Classifier: Development Status :: 5 - Production/Stable
Classifier: Environment :: Web Environment
Classifier: Framework :: Django
Classifier: Intended Audience :: Developers
Classifier: License :: OSI Approved :: MIT License
Classifier: Programming Language :: Python
Classifier: Programming Language :: Python :: 3
Classifier: Topic :: Software Development :: Libraries :: Python Modules
Requires-Dist: Django (>=1.11)
